spacy_ewc/__init__.py
spacy_ewc/ewc/__init__.py
spacy_ewc/ewc/ewc.py
spacy_ewc/ewc/vector_dict.py
spacy_ewc/ner_trainer/__init__.py
spacy_ewc/ner_trainer/ewc_ner_trainer.py
spacy_ewc/spacy_wrapper/__init__.py
spacy_ewc/spacy_wrapper/ewc_spacy_wrapper.py
spacy_ewc/utils/__init__.py
spacy_ewc/utils/extract_labels.py
spacy_ewc/utils/generate_spacy_entities.py
spacy_ewc-0.1.1.dist-info/AUTHORS
spacy_ewc-0.1.1.dist-info/LICENSE
spacy_ewc-0.1.1.dist-info/METADATA
spacy_ewc-0.1.1.dist-info/WHEEL
spacy_ewc-0.1.1.dist-info/top_level.txt
spacy_ewc-0.1.1.dist-info/RECORD
