Metadata-Version: 2.1
Name: spacy-ewc
Version: 0.1.1
Summary: A spaCy library for Named Entity Recognition with Elastic Weight Consolidation.
Author-email: DarkRockMountain <dev@darkrockmountain.com>
License: MIT
Project-URL: homepage, https://github.com/darkrockmountain/spacy-ewc
Project-URL: repository, https://github.com/darkrockmountain/spacy-ewc
Project-URL: documentation, https://github.com/darkrockmountain/spacy-ewc#readme
Requires-Python: >=3.7
License-File: LICENSE
License-File: AUTHORS
Requires-Dist: spacy>=3.0.0
Requires-Dist: numpy>=2.0.2
Provides-Extra: dev
Requires-Dist: pytest; extra == "dev"
Requires-Dist: pytest-cov; extra == "dev"
Requires-Dist: spacy-lookups-data; extra == "dev"
Requires-Dist: flake8; extra == "dev"
Requires-Dist: black; extra == "dev"
Provides-Extra: docs
Requires-Dist: sphinx; extra == "docs"
